CHANGES.txt
MANIFEST.in
README.txt
setup.cfg
setup.py
docs/HISTORY.txt
docs/Makefile
docs/WISHLIST.txt
docs/conf.py
docs/index.rst
docs/intro.rst
docs/make.bat
docs/naming.rst
docs/reloading.rst
quantumcore/__init__.py
quantumcore.resources.egg-info/PKG-INFO
quantumcore.resources.egg-info/SOURCES.txt
quantumcore.resources.egg-info/dependency_links.txt
quantumcore.resources.egg-info/entry_points.txt
quantumcore.resources.egg-info/namespace_packages.txt
quantumcore.resources.egg-info/not-zip-safe
quantumcore.resources.egg-info/paster_plugins.txt
quantumcore.resources.egg-info/requires.txt
quantumcore.resources.egg-info/top_level.txt
quantumcore/resources/__init__.py
quantumcore/resources/cluster.py
quantumcore/resources/css_resource.py
quantumcore/resources/js_resource.py
quantumcore/resources/jsmin.py
quantumcore/resources/jst_resource.py
quantumcore/resources/resource.py
quantumcore/resources/resources.py
quantumcore/resources/tests/__init__.py
quantumcore/resources/tests/conftest.py
quantumcore/resources/tests/test_linking_css.py
quantumcore/resources/tests/test_linking_js.py
quantumcore/resources/tests/test_minify_js.py
quantumcore/resources/tests/test_ordering.py
quantumcore/resources/tests/test_rendering_css.py
quantumcore/resources/tests/data/addons.css
quantumcore/resources/tests/data/ie.css
quantumcore/resources/tests/data/print.css
quantumcore/resources/tests/data/script1.js
quantumcore/resources/tests/data/script2.js
quantumcore/resources/tests/data/script3.js
quantumcore/resources/tests/data/style.css