Metadata-Version: 1.0
Name: quantumcore.resources
Version: 0.5.4
Summary: A resource manager for CSS and JS
Home-page: http://quantumcore.org
Author: Christian Scholz
Author-email: cs@comlounge.net
License: MIT
Keywords: resources web manager registry css js javascript templates quantumcore
Platform: UNKNOWN
Classifier: Programming Language :: Python
Classifier: Topic :: Software Development :: Libraries :: Python Modules
Classifier: Development Status :: 4 - Beta
Classifier: Environment :: Web Environment
Classifier: Intended Audience :: Developers
Classifier: License :: OSI Approved :: MIT License
Classifier: Operating System :: OS Independent
Classifier: Topic :: Internet :: WWW/HTTP :: WSGI
Classifier: Topic :: Internet :: WWW/HTTP
Classifier: Topic :: Utilities
